fastapi_manager/__init__.py
fastapi_manager/manager.py
fastapi_manager/version.py
fastapi_manager-2.0.3.dist-info/LICENSE
fastapi_manager-2.0.3.dist-info/METADATA
fastapi_manager-2.0.3.dist-info/WHEEL
fastapi_manager-2.0.3.dist-info/top_level.txt
fastapi_manager-2.0.3.dist-info/RECORD
